bib/__init__.py
bib/admin.py
bib/api_views.py
bib/apps.py
bib/dal_views.py
bib/models.py
bib/serializers.py
bib/tests.py
bib/urls.py
bib/views.py
bib/zot_utils.py
bib/management/__init__.py
bib/management/commands/bib_import.py
bib/management/commands/bib_update.py
bib/management/commands/sync_to_zotero.py
bib/migrations/0001_initial.py
bib/migrations/__init__.py
bib/templates/bib/base.html
bib/templates/bib/synczotero.html
bib/templates/bib/synczotero_action.html
bib/templates/bib/tags/zotitem.html
bib/templatetags/__init__.py
bib/templatetags/bib_extras.py
acdh_django_zotero-0.1.6.dist-info/AUTHORS.rst
acdh_django_zotero-0.1.6.dist-info/LICENSE
acdh_django_zotero-0.1.6.dist-info/METADATA
acdh_django_zotero-0.1.6.dist-info/WHEEL
acdh_django_zotero-0.1.6.dist-info/top_level.txt
acdh_django_zotero-0.1.6.dist-info/RECORD
